{"tag_id":"28BP","ring_number":"AA17269","scientific_name":"Cossypha natalensis","common_name":"Red-capped Robin-Chat","species_code":"rcrcha1","in_ebirdst":false,"manufacturer":"Swiss Ornithological Institute","model":"GDL3pam-v2.3","firmware":"FW_GDL3pam_V2.4.1","weight":"1.49","attachment_type":"leg harness|material:cord|attachement:tubes","readout_method":"","tag_comments":"","project_id":"16804931","sex":null,"age_class":"1yr","wing_length":92.0,"paths":{"type":["simulation","simulation","simulation","simulation","simulation","simulation","simulation","simulation","simulation","simulation","simulation","simulation","simulation","simulation","simulation","simulation","simulation","simulation","simulation","simulation","simulation","simulation","simulation","simulation","simulation","simulation","simulation","simulation","simulation","simulation","simulation","simulation","simulation","simulation","simulation","simulation","simulation","simulation","simulation","simulation","simulation","simulation","simulation","simulation","simulation","simulation","simulation","simulation","simulation","simulation","simulation","simulation","simulation","simulation","simulation","simulation","simulation","simulation","simulation","simulation","simulation","simulation","simulation","simulation","simulation","simulation","simulation","simulation","simulation","simulation","simulation","simulation","simulation","simulation","simulation","simulation","simulation","simulation","simulation","simulation","simulation","simulation","simulation","simulation","simulation","simulation","simulation","simulation","simulation","simulation","simulation","simulation","simulation","simulation","simulation","simulation","simulation","simulation","simulation","simulation","simulation","simulation","simulation","simulation","simulation","simulation","simulation","simulation","simulation","simulation","simulation","simulation","simulation","simulation","simulation","simulation","simulation","simulation","simulation","simulation","simulation","simulation","simulation","simulation","simulation","simulation","simulation","simulation","simulation","simulation","simulation","simulation","simulation","simulation","simulation","simulation","simulation","simulation","simulation","simulation","most_likely","most_likely","most_likely","most_likely","most_likely","most_likely","most_likely","most_likely","most_likely","most_likely","most_likely","most_likely","most_likely","most_likely"],"stap_id":[1,1,1,1,1,1,1,1,1,1,2,2,2,2,2,2,2,2,2,2,3,3,3,3,3,3,3,3,3,3,4,4,4,4,4,4,4,4,4,4,5,5,5,5,5,5,5,5,5,5,6,6,6,6,6,6,6,6,6,6,7,7,7,7,7,7,7,7,7,7,8,8,8,8,8,8,8,8,8,8,9,9,9,9,9,9,9,9,9,9,10,10,10,10,10,10,10,10,10,10,11,11,11,11,11,11,11,11,11,11,12,12,12,12,12,12,12,12,12,12,13,13,13,13,13,13,13,13,13,13,14,14,14,14,14,14,14,14,14,14,1,2,3,4,5,6,7,8,9,10,11,12,13,14],"lat":[-3.3783,-3.3783,-3.3783,-3.3783,-3.3783,-3.3783,-3.3783,-3.3783,-3.3783,-3.3783,-7.95,-5.85,-9.25,-6.95,-7.95,-5.45,-8.55,-8.55,-3.05,-6.25,-10.95,-11.75,-10.85,-10.95,-10.55,-8.95,-10.55,-10.35,-8.95,-10.15,-10.65,-12.05,-11.05,-11.85,-10.55,-10.35,-10.75,-10.55,-9.45,-10.75,-10.45,-12.05,-12.15,-12.45,-11.65,-10.85,-10.75,-10.25,-10.85,-10.25,-10.95,-12.55,-13.75,-12.35,-11.75,-9.55,-11.95,-10.05,-9.85,-11.45,-13.25,-12.15,-13.55,-12.45,-13.25,-12.05,-12.35,-11.55,-12.35,-13.25,-13.55,-12.15,-13.65,-12.65,-13.05,-11.95,-12.85,-11.85,-12.25,-13.35,-7.25,-11.85,-7.95,-7.15,-7.35,-11.05,-8.75,-9.25,-7.75,-10.45,-4.55,-5.95,-3.95,-4.55,-4.65,-6.25,-3.95,-4.05,-4.35,-6.25,-3.65,-5.15,-3.55,-4.25,-4.55,-4.45,-3.55,-3.85,-4.65,-5.05,-3.75,-3.95,-3.85,-3.85,-3.75,-4.35,-3.85,-3.85,-4.15,-3.85,-3.65,-3.35,-3.75,-3.35,-3.35,-3.65,-3.55,-3.45,-3.75,-3.45,-3.3783,-3.3783,-3.3783,-3.3783,-3.3783,-3.3783,-3.3783,-3.3783,-3.3783,-3.3783,-3.3783,-6.35,-9.45,-10.05,-10.55,-11.45,-12.85,-13.05,-8.65,-4.65,-3.75,-3.85,-3.45,-3.3783],"lon":[39.9889,39.9889,39.9889,39.9889,39.9889,39.9889,39.9889,39.9889,39.9889,39.9889,39.65,39.25,39.45,39.35,39.15,39.75,39.25,39.25,40.05,39.45,40.45,40.35,40.45,40.45,40.15,39.45,40.25,40.05,39.25,39.75,40.45,40.45,40.05,39.85,40.05,39.95,39.85,40.35,39.25,39.95,39.95,40.15,39.75,39.65,40.15,39.35,39.55,39.75,39.15,39.75,39.15,39.35,40.15,40.05,39.65,38.65,39.55,39.35,39.55,39.35,40.35,40.45,40.25,40.45,40.45,40.15,40.35,40.35,40.35,40.45,40.35,40.25,40.45,40.25,40.35,40.05,40.35,40.15,40.35,40.35,38.95,39.85,38.95,39.25,39.15,40.25,39.25,39.45,39.15,40.25,39.15,39.25,39.45,39.15,39.25,39.45,39.45,39.55,39.45,39.15,39.65,39.65,39.85,39.45,39.25,39.25,39.85,39.75,39.15,39.75,39.75,39.65,39.55,39.75,39.75,39.45,39.75,39.65,39.45,39.65,39.75,39.75,39.75,39.85,39.95,39.65,39.75,39.75,39.75,39.85,39.9889,39.9889,39.9889,39.9889,39.9889,39.9889,39.9889,39.9889,39.9889,39.9889,39.9889,39.45,39.45,39.55,39.95,39.35,40.35,40.45,39.15,39.25,39.75,39.75,39.75,39.9889]},"staps":{"stap_id":[1,2,3,4,5,6,7,8,9,10,11,12,13,14],"start":["2021-08-09T23:57:00Z","2021-12-19T01:37:00Z","2021-12-20T01:17:00Z","2021-12-20T21:57:00Z","2021-12-21T23:42:00Z","2021-12-29T02:07:00Z","2021-12-30T00:12:00Z","2021-12-30T23:47:00Z","2022-05-28T01:37:00Z","2022-05-29T01:57:00Z","2022-05-29T21:42:00Z","2022-05-30T22:17:00Z","2022-06-03T23:52:00Z","2022-06-04T21:52:00Z"],"end":["2021-12-18T18:57:00Z","2021-12-19T18:17:00Z","2021-12-20T19:52:00Z","2021-12-21T21:12:00Z","2021-12-28T23:22:00Z","2021-12-29T18:27:00Z","2021-12-30T23:02:00Z","2022-05-27T17:17:00Z","2022-05-28T17:07:00Z","2022-05-29T19:12:00Z","2022-05-30T20:47:00Z","2022-06-03T23:02:00Z","2022-06-04T21:12:00Z","2022-08-10T23:57:00Z"],"include":[true,true,true,true,true,true,true,true,true,true,true,true,true,true]},"observations":[{"datetime":"2021-08-10T07:00:00+00:00","observation_type":"equipment","latitude":39.988903,"longitude":-3.37827,"location_name":"Mwamba","sex":"U","age_class":"1yr","wing_length":92.0},{"datetime":"2022-08-11T07:00:00+00:00","observation_type":"retrieval","latitude":39.988903,"longitude":-3.37827,"location_name":"Mwamba","sex":"U","age_class":">1yr","wing_length":94.0}],"pressurepath":{}}