{"tags":[{"tag_id":"22BS","scientific_name":"Caprimulgus europaeus","common_name":"Eurasian Nightjar","species_code":"eurnig1","in_ebirdst":true,"sex":"M","age_class":">1yr","wing_length":197.0,"staps":[{"stap_id":"1","longitude":110.83,"latitude":48.57,"duration_days":35.67,"start":"2018-07-14T23:57:30+00:00","end":"2018-08-19T16:07:30+00:00"},{"stap_id":"2","longitude":109.25,"latitude":47.25,"duration_days":0.03,"start":"2018-08-19T19:07:30+00:00","end":"2018-08-19T19:52:30+00:00"},{"stap_id":"3","longitude":109.25,"latitude":47.25,"duration_days":7.7,"start":"2018-08-19T20:27:30+00:00","end":"2018-08-27T13:22:30+00:00"},{"stap_id":"4","longitude":105.25,"latitude":45.25,"duration_days":1.65,"start":"2018-08-27T20:27:30+00:00","end":"2018-08-29T12:07:30+00:00"},{"stap_id":"5","longitude":99.75,"latitude":44.75,"duration_days":1.7,"start":"2018-08-29T20:32:30+00:00","end":"2018-08-31T13:22:30+00:00"},{"stap_id":"6","longitude":98.75,"latitude":44.75,"duration_days":1.19,"start":"2018-08-31T15:52:30+00:00","end":"2018-09-01T20:27:30+00:00"},{"stap_id":"7","longitude":98.25,"latitude":44.75,"duration_days":0.74,"start":"2018-09-01T21:37:30+00:00","end":"2018-09-02T15:17:30+00:00"},{"stap_id":"8","longitude":96.75,"latitude":44.25,"duration_days":2.77,"start":"2018-09-02T18:57:30+00:00","end":"2018-09-05T13:32:30+00:00"},{"stap_id":"9","longitude":90.75,"latitude":44.75,"duration_days":0.63,"start":"2018-09-05T22:32:30+00:00","end":"2018-09-06T13:37:30+00:00"},{"stap_id":"10","longitude":83.25,"latitude":45.75,"duration_days":0.62,"start":"2018-09-06T22:52:30+00:00","end":"2018-09-07T13:52:30+00:00"},{"stap_id":"11","longitude":75.75,"latitude":43.25,"duration_days":0.58,"start":"2018-09-07T23:27:30+00:00","end":"2018-09-08T13:27:30+00:00"},{"stap_id":"12","longitude":74.75,"latitude":42.25,"duration_days":0.65,"start":"2018-09-08T22:07:30+00:00","end":"2018-09-09T13:37:30+00:00"},{"stap_id":"13","longitude":71.75,"latitude":42.75,"duration_days":0.61,"start":"2018-09-09T23:47:30+00:00","end":"2018-09-10T14:32:30+00:00"},{"stap_id":"14","longitude":70.75,"latitude":41.25,"duration_days":16.81,"start":"2018-09-10T22:42:30+00:00","end":"2018-09-27T18:12:30+00:00"},{"stap_id":"15","longitude":69.25,"latitude":40.75,"duration_days":0.59,"start":"2018-09-27T23:37:30+00:00","end":"2018-09-28T13:42:30+00:00"},{"stap_id":"16","longitude":67.25,"latitude":38.75,"duration_days":0.57,"start":"2018-09-29T00:07:30+00:00","end":"2018-09-29T13:47:30+00:00"},{"stap_id":"17","longitude":65.75,"latitude":36.25,"duration_days":0.59,"start":"2018-09-29T23:52:30+00:00","end":"2018-09-30T14:07:30+00:00"},{"stap_id":"18","longitude":62.25,"latitude":34.75,"duration_days":0.57,"start":"2018-10-01T00:57:30+00:00","end":"2018-10-01T14:32:30+00:00"},{"stap_id":"19","longitude":61.25,"latitude":29.25,"duration_days":0.58,"start":"2018-10-02T00:17:30+00:00","end":"2018-10-02T14:07:30+00:00"},{"stap_id":"20","longitude":60.25,"latitude":25.75,"duration_days":0.63,"start":"2018-10-03T01:22:30+00:00","end":"2018-10-03T16:27:30+00:00"},{"stap_id":"21","longitude":60.75,"latitude":25.25,"duration_days":0.83,"start":"2018-10-03T18:07:30+00:00","end":"2018-10-04T14:02:30+00:00"},{"stap_id":"22","longitude":56.25,"latitude":23.75,"duration_days":0.64,"start":"2018-10-04T22:47:30+00:00","end":"2018-10-05T14:12:30+00:00"},{"stap_id":"23","longitude":55.25,"latitude":18.25,"duration_days":0.55,"start":"2018-10-06T01:27:30+00:00","end":"2018-10-06T14:42:30+00:00"},{"stap_id":"24","longitude":51.75,"latitude":17.25,"duration_days":0.72,"start":"2018-10-06T21:47:30+00:00","end":"2018-10-07T15:07:30+00:00"},{"stap_id":"25","longitude":47.75,"latitude":13.75,"duration_days":0.57,"start":"2018-10-08T01:52:30+00:00","end":"2018-10-08T15:27:30+00:00"},{"stap_id":"26","longitude":46.25,"latitude":9.25,"duration_days":0.57,"start":"2018-10-09T01:57:30+00:00","end":"2018-10-09T15:37:30+00:00"},{"stap_id":"27","longitude":46.25,"latitude":4.25,"duration_days":6.9,"start":"2018-10-10T01:42:30+00:00","end":"2018-10-16T23:17:30+00:00"},{"stap_id":"28","longitude":46.25,"latitude":4.25,"duration_days":5.74,"start":"2018-10-17T00:12:30+00:00","end":"2018-10-22T18:02:30+00:00"},{"stap_id":"29","longitude":45.75,"latitude":4.25,"duration_days":2.19,"start":"2018-10-22T20:02:30+00:00","end":"2018-10-25T00:42:30+00:00"},{"stap_id":"30","longitude":45.75,"latitude":4.25,"duration_days":1.8,"start":"2018-10-25T01:52:30+00:00","end":"2018-10-26T21:02:30+00:00"},{"stap_id":"31","longitude":45.75,"latitude":4.25,"duration_days":1.77,"start":"2018-10-26T22:12:30+00:00","end":"2018-10-28T16:47:30+00:00"},{"stap_id":"32","longitude":45.25,"latitude":3.75,"duration_days":2.9,"start":"2018-10-28T18:32:30+00:00","end":"2018-10-31T16:02:30+00:00"},{"stap_id":"33","longitude":41.25,"latitude":-0.75,"duration_days":0.66,"start":"2018-11-01T01:52:30+00:00","end":"2018-11-01T17:42:30+00:00"},{"stap_id":"34","longitude":40.25,"latitude":-1.25,"duration_days":0.88,"start":"2018-11-01T20:37:30+00:00","end":"2018-11-02T17:47:30+00:00"},{"stap_id":"35","longitude":39.75,"latitude":-1.25,"duration_days":0.05,"start":"2018-11-02T19:07:30+00:00","end":"2018-11-02T20:22:30+00:00"},{"stap_id":"36","longitude":38.75,"latitude":-2.25,"duration_days":16.64,"start":"2018-11-03T01:12:30+00:00","end":"2018-11-19T16:27:30+00:00"},{"stap_id":"37","longitude":38.25,"latitude":-4.25,"duration_days":0.07,"start":"2018-11-19T22:57:30+00:00","end":"2018-11-20T00:37:30+00:00"},{"stap_id":"38","longitude":38.25,"latitude":-4.75,"duration_days":0.62,"start":"2018-11-20T02:27:30+00:00","end":"2018-11-20T17:22:30+00:00"},{"stap_id":"39","longitude":37.75,"latitude":-6.25,"duration_days":0.97,"start":"2018-11-20T23:02:30+00:00","end":"2018-11-21T22:12:30+00:00"},{"stap_id":"40","longitude":37.25,"latitude":-7.75,"duration_days":0.65,"start":"2018-11-22T02:27:30+00:00","end":"2018-11-22T18:02:30+00:00"},{"stap_id":"41","longitude":34.75,"latitude":-11.25,"duration_days":0.69,"start":"2018-11-23T02:07:30+00:00","end":"2018-11-23T18:42:30+00:00"},{"stap_id":"42","longitude":32.25,"latitude":-13.25,"duration_days":0.03,"start":"2018-11-24T01:42:30+00:00","end":"2018-11-24T02:27:30+00:00"},{"stap_id":"43","longitude":32.25,"latitude":-13.25,"duration_days":0.58,"start":"2018-11-24T02:52:30+00:00","end":"2018-11-24T16:52:30+00:00"},{"stap_id":"44","longitude":30.75,"latitude":-14.75,"duration_days":0.86,"start":"2018-11-24T21:37:30+00:00","end":"2018-11-25T18:22:30+00:00"},{"stap_id":"45","longitude":30.75,"latitude":-14.75,"duration_days":109.03,"start":"2018-11-25T19:27:30+00:00","end":"2019-03-14T20:17:30+00:00"},{"stap_id":"46","longitude":32.75,"latitude":-16.25,"duration_days":0.8,"start":"2019-03-15T03:17:30+00:00","end":"2019-03-15T22:32:30+00:00"},{"stap_id":"47","longitude":32.75,"latitude":-16.75,"duration_days":0.94,"start":"2019-03-16T00:47:30+00:00","end":"2019-03-16T23:27:30+00:00"},{"stap_id":"48","longitude":32.75,"latitude":-16.75,"duration_days":3.66,"start":"2019-03-17T00:27:30+00:00","end":"2019-03-20T16:12:30+00:00"},{"stap_id":"49","longitude":34.75,"latitude":-14.25,"duration_days":1.56,"start":"2019-03-21T02:22:30+00:00","end":"2019-03-22T15:52:30+00:00"},{"stap_id":"50","longitude":35.25,"latitude":-11.25,"duration_days":0.54,"start":"2019-03-23T02:52:30+00:00","end":"2019-03-23T15:52:30+00:00"},{"stap_id":"51","longitude":35.75,"latitude":-8.75,"duration_days":0.54,"start":"2019-03-24T02:57:30+00:00","end":"2019-03-24T15:52:30+00:00"},{"stap_id":"52","longitude":37.75,"latitude":-7.25,"duration_days":0.55,"start":"2019-03-25T02:47:30+00:00","end":"2019-03-25T15:57:30+00:00"},{"stap_id":"53","longitude":39.25,"latitude":-4.75,"duration_days":0.72,"start":"2019-03-26T01:12:30+00:00","end":"2019-03-26T18:32:30+00:00"},{"stap_id":"54","longitude":39.25,"latitude":-4.25,"duration_days":0.83,"start":"2019-03-26T20:52:30+00:00","end":"2019-03-27T16:47:30+00:00"},{"stap_id":"55","longitude":39.25,"latitude":-2.75,"duration_days":0.97,"start":"2019-03-27T21:27:30+00:00","end":"2019-03-28T20:47:30+00:00"},{"stap_id":"56","longitude":39.25,"latitude":-2.25,"duration_days":1.87,"start":"2019-03-28T22:17:30+00:00","end":"2019-03-30T19:12:30+00:00"},{"stap_id":"57","longitude":38.75,"latitude":-2.25,"duration_days":0.75,"start":"2019-03-30T20:52:30+00:00","end":"2019-03-31T14:47:30+00:00"}]},{"tag_id":"22BT","scientific_name":"Caprimulgus europaeus","common_name":"Eurasian Nightjar","species_code":"eurnig1","in_ebirdst":true,"sex":"M","age_class":">1yr","wing_length":198.0,"staps":[{"stap_id":"1","longitude":110.83,"latitude":48.57,"duration_days":42.52,"start":"2018-07-14T23:57:30+00:00","end":"2018-08-26T12:32:30+00:00"},{"stap_id":"2","longitude":106.25,"latitude":46.25,"duration_days":0.7,"start":"2018-08-26T19:47:30+00:00","end":"2018-08-27T12:37:30+00:00"},{"stap_id":"3","longitude":101.25,"latitude":45.25,"duration_days":0.69,"start":"2018-08-27T20:37:30+00:00","end":"2018-08-28T13:07:30+00:00"},{"stap_id":"4","longitude":99.75,"latitude":45.75,"duration_days":0.1,"start":"2018-08-28T15:47:30+00:00","end":"2018-08-28T18:07:30+00:00"},{"stap_id":"5","longitude":98.75,"latitude":45.75,"duration_days":0.75,"start":"2018-08-28T19:57:30+00:00","end":"2018-08-29T13:52:30+00:00"},{"stap_id":"6","longitude":98.25,"latitude":45.75,"duration_days":0.23,"start":"2018-08-29T14:52:30+00:00","end":"2018-08-29T20:27:30+00:00"},{"stap_id":"7","longitude":97.75,"latitude":45.75,"duration_days":0.64,"start":"2018-08-29T21:22:30+00:00","end":"2018-08-30T12:37:30+00:00"},{"stap_id":"8","longitude":92.75,"latitude":46.25,"duration_days":0.6,"start":"2018-08-30T22:27:30+00:00","end":"2018-08-31T12:52:30+00:00"},{"stap_id":"9","longitude":92.75,"latitude":46.75,"duration_days":0.03,"start":"2018-08-31T14:42:30+00:00","end":"2018-08-31T15:22:30+00:00"},{"stap_id":"10","longitude":92.25,"latitude":46.75,"duration_days":0.06,"start":"2018-08-31T17:07:30+00:00","end":"2018-08-31T18:27:30+00:00"},{"stap_id":"11","longitude":91.25,"latitude":46.75,"duration_days":0.62,"start":"2018-08-31T21:52:30+00:00","end":"2018-09-01T12:52:30+00:00"},{"stap_id":"12","longitude":90.25,"latitude":46.25,"duration_days":0.86,"start":"2018-09-01T17:37:30+00:00","end":"2018-09-02T14:12:30+00:00"},{"stap_id":"13","longitude":90.25,"latitude":45.75,"duration_days":0.05,"start":"2018-09-02T15:22:30+00:00","end":"2018-09-02T16:32:30+00:00"},{"stap_id":"14","longitude":89.25,"latitude":44.75,"duration_days":1.77,"start":"2018-09-02T19:42:30+00:00","end":"2018-09-04T14:07:30+00:00"},{"stap_id":"15","longitude":84.25,"latitude":45.25,"duration_days":0.62,"start":"2018-09-04T23:17:30+00:00","end":"2018-09-05T14:17:30+00:00"},{"stap_id":"16","longitude":80.25,"latitude":44.75,"duration_days":0.67,"start":"2018-09-05T23:17:30+00:00","end":"2018-09-06T15:27:30+00:00"},{"stap_id":"17","longitude":79.25,"latitude":44.25,"duration_days":0.05,"start":"2018-09-06T18:37:30+00:00","end":"2018-09-06T19:52:30+00:00"},{"stap_id":"18","longitude":78.75,"latitude":44.75,"duration_days":0.69,"start":"2018-09-06T22:27:30+00:00","end":"2018-09-07T14:57:30+00:00"},{"stap_id":"19","longitude":75.25,"latitude":43.75,"duration_days":0.82,"start":"2018-09-07T23:57:30+00:00","end":"2018-09-08T19:37:30+00:00"},{"stap_id":"20","longitude":74.25,"latitude":43.25,"duration_days":0.62,"start":"2018-09-09T00:22:30+00:00","end":"2018-09-09T15:17:30+00:00"},{"stap_id":"21","longitude":70.25,"latitude":43.25,"duration_days":0.69,"start":"2018-09-09T22:52:30+00:00","end":"2018-09-10T15:27:30+00:00"},{"stap_id":"22","longitude":68.25,"latitude":41.75,"duration_days":0.57,"start":"2018-09-11T00:32:30+00:00","end":"2018-09-11T14:07:30+00:00"},{"stap_id":"23","longitude":67.75,"latitude":39.25,"duration_days":0.56,"start":"2018-09-12T00:42:30+00:00","end":"2018-09-12T14:07:30+00:00"},{"stap_id":"24","longitude":67.75,"latitude":39.25,"duration_days":0.2,"start":"2018-09-12T14:47:30+00:00","end":"2018-09-12T19:37:30+00:00"},{"stap_id":"25","longitude":68.25,"latitude":39.25,"duration_days":0.11,"start":"2018-09-12T20:47:30+00:00","end":"2018-09-12T23:22:30+00:00"},{"stap_id":"26","longitude":68.75,"latitude":39.25,"duration_days":0.55,"start":"2018-09-13T00:42:30+00:00","end":"2018-09-13T13:57:30+00:00"},{"stap_id":"27","longitude":68.75,"latitude":39.25,"duration_days":1.02,"start":"2018-09-13T14:27:30+00:00","end":"2018-09-14T14:57:30+00:00"},{"stap_id":"28","longitude":68.75,"latitude":38.75,"duration_days":0.88,"start":"2018-09-14T16:42:30+00:00","end":"2018-09-15T13:52:30+00:00"},{"stap_id":"29","longitude":69.25,"latitude":38.75,"duration_days":0.95,"start":"2018-09-15T15:07:30+00:00","end":"2018-09-16T13:57:30+00:00"},{"stap_id":"30","longitude":69.25,"latitude":38.75,"duration_days":0.42,"start":"2018-09-16T14:22:30+00:00","end":"2018-09-17T00:27:30+00:00"},{"stap_id":"31","longitude":69.25,"latitude":38.75,"duration_days":0.55,"start":"2018-09-17T00:42:30+00:00","end":"2018-09-17T13:52:30+00:00"},{"stap_id":"32","longitude":69.25,"latitude":38.75,"duration_days":0.08,"start":"2018-09-17T14:32:30+00:00","end":"2018-09-17T16:27:30+00:00"},{"stap_id":"33","longitude":68.25,"latitude":38.75,"duration_days":0.12,"start":"2018-09-17T19:37:30+00:00","end":"2018-09-17T22:32:30+00:00"},{"stap_id":"34","longitude":67.75,"latitude":38.75,"duration_days":0.61,"start":"2018-09-18T00:32:30+00:00","end":"2018-09-18T15:12:30+00:00"},{"stap_id":"35","longitude":67.75,"latitude":38.75,"duration_days":12.9,"start":"2018-09-18T16:02:30+00:00","end":"2018-10-01T13:32:30+00:00"},{"stap_id":"36","longitude":66.25,"latitude":37.75,"duration_days":0.76,"start":"2018-10-01T20:02:30+00:00","end":"2018-10-02T14:12:30+00:00"},{"stap_id":"37","longitude":62.25,"latitude":34.75,"duration_days":0.53,"start":"2018-10-03T01:07:30+00:00","end":"2018-10-03T13:57:30+00:00"},{"stap_id":"38","longitude":62.75,"latitude":28.25,"duration_days":0.6,"start":"2018-10-04T00:52:30+00:00","end":"2018-10-04T15:17:30+00:00"},{"stap_id":"39","longitude":63.25,"latitude":25.75,"duration_days":0.65,"start":"2018-10-04T22:52:30+00:00","end":"2018-10-05T14:22:30+00:00"},{"stap_id":"40","longitude":59.75,"latitude":22.25,"duration_days":0.57,"start":"2018-10-06T01:07:30+00:00","end":"2018-10-06T14:52:30+00:00"},{"stap_id":"41","longitude":53.25,"latitude":19.75,"duration_days":0.55,"start":"2018-10-07T01:52:30+00:00","end":"2018-10-07T15:07:30+00:00"},{"stap_id":"42","longitude":49.25,"latitude":16.25,"duration_days":0.59,"start":"2018-10-08T01:27:30+00:00","end":"2018-10-08T15:42:30+00:00"},{"stap_id":"43","longitude":47.75,"latitude":13.75,"duration_days":0.72,"start":"2018-10-08T21:57:30+00:00","end":"2018-10-09T15:07:30+00:00"},{"stap_id":"44","longitude":42.75,"latitude":10.25,"duration_days":0.66,"start":"2018-10-10T00:22:30+00:00","end":"2018-10-10T16:07:30+00:00"},{"stap_id":"45","longitude":42.25,"latitude":7.75,"duration_days":6.91,"start":"2018-10-10T23:57:30+00:00","end":"2018-10-17T21:52:30+00:00"},{"stap_id":"46","longitude":42.25,"latitude":7.25,"duration_days":8.04,"start":"2018-10-17T23:42:30+00:00","end":"2018-10-26T00:37:30+00:00"},{"stap_id":"47","longitude":42.25,"latitude":6.75,"duration_days":0.53,"start":"2018-10-26T02:07:30+00:00","end":"2018-10-26T14:47:30+00:00"},{"stap_id":"48","longitude":42.25,"latitude":5.75,"duration_days":0.81,"start":"2018-10-26T19:32:30+00:00","end":"2018-10-27T14:52:30+00:00"},{"stap_id":"49","longitude":42.25,"latitude":4.75,"duration_days":0.93,"start":"2018-10-27T20:07:30+00:00","end":"2018-10-28T18:32:30+00:00"},{"stap_id":"50","longitude":41.75,"latitude":1.75,"duration_days":1.68,"start":"2018-10-29T02:22:30+00:00","end":"2018-10-30T18:47:30+00:00"},{"stap_id":"51","longitude":40.75,"latitude":1.25,"duration_days":16.69,"start":"2018-10-30T22:42:30+00:00","end":"2018-11-16T15:22:30+00:00"},{"stap_id":"52","longitude":39.75,"latitude":0.25,"duration_days":4.86,"start":"2018-11-16T19:22:30+00:00","end":"2018-11-21T15:57:30+00:00"},{"stap_id":"53","longitude":39.25,"latitude":-0.75,"duration_days":0.81,"start":"2018-11-21T20:07:30+00:00","end":"2018-11-22T15:32:30+00:00"},{"stap_id":"54","longitude":38.25,"latitude":-6.75,"duration_days":0.75,"start":"2018-11-23T02:47:30+00:00","end":"2018-11-23T20:47:30+00:00"},{"stap_id":"55","longitude":36.25,"latitude":-8.75,"duration_days":0.58,"start":"2018-11-24T02:47:30+00:00","end":"2018-11-24T16:42:30+00:00"},{"stap_id":"56","longitude":33.75,"latitude":-12.75,"duration_days":2.61,"start":"2018-11-25T02:22:30+00:00","end":"2018-11-27T17:02:30+00:00"},{"stap_id":"57","longitude":33.75,"latitude":-17.75,"duration_days":0.61,"start":"2018-11-28T02:47:30+00:00","end":"2018-11-28T17:22:30+00:00"},{"stap_id":"58","longitude":33.75,"latitude":-19.75,"duration_days":1.79,"start":"2018-11-28T22:12:30+00:00","end":"2018-11-30T17:07:30+00:00"},{"stap_id":"59","longitude":31.25,"latitude":-23.25,"duration_days":0.82,"start":"2018-12-01T02:12:30+00:00","end":"2018-12-01T21:47:30+00:00"},{"stap_id":"60","longitude":30.25,"latitude":-24.75,"duration_days":0.69,"start":"2018-12-02T02:02:30+00:00","end":"2018-12-02T18:32:30+00:00"},{"stap_id":"61","longitude":30.25,"latitude":-28.25,"duration_days":0.68,"start":"2018-12-03T02:22:30+00:00","end":"2018-12-03T18:42:30+00:00"},{"stap_id":"62","longitude":29.25,"latitude":-31.75,"duration_days":0.66,"start":"2018-12-04T03:12:30+00:00","end":"2018-12-04T19:07:30+00:00"},{"stap_id":"63","longitude":27.75,"latitude":-32.75,"duration_days":117.62,"start":"2018-12-05T01:57:30+00:00","end":"2019-04-01T16:47:30+00:00"},{"stap_id":"64","longitude":32.25,"latitude":-28.75,"duration_days":0.55,"start":"2019-04-02T03:32:30+00:00","end":"2019-04-02T16:47:30+00:00"},{"stap_id":"65","longitude":32.75,"latitude":-25.75,"duration_days":0.67,"start":"2019-04-03T00:37:30+00:00","end":"2019-04-03T16:42:30+00:00"},{"stap_id":"66","longitude":34.75,"latitude":-24.25,"duration_days":0.58,"start":"2019-04-04T03:12:30+00:00","end":"2019-04-04T17:02:30+00:00"},{"stap_id":"67","longitude":35.25,"latitude":-22.75,"duration_days":0.72,"start":"2019-04-05T00:22:30+00:00","end":"2019-04-05T17:32:30+00:00"},{"stap_id":"68","longitude":35.25,"latitude":-21.75,"duration_days":0.81,"start":"2019-04-05T23:32:30+00:00","end":"2019-04-06T18:52:30+00:00"},{"stap_id":"69","longitude":35.75,"latitude":-18.75,"duration_days":0.58,"start":"2019-04-07T03:17:30+00:00","end":"2019-04-07T17:07:30+00:00"},{"stap_id":"70","longitude":36.75,"latitude":-16.25,"duration_days":0.69,"start":"2019-04-08T00:17:30+00:00","end":"2019-04-08T16:52:30+00:00"},{"stap_id":"71","longitude":37.75,"latitude":-14.25,"duration_days":0.59,"start":"2019-04-09T02:52:30+00:00","end":"2019-04-09T17:07:30+00:00"},{"stap_id":"72","longitude":37.75,"latitude":-13.75,"duration_days":0.17,"start":"2019-04-09T19:42:30+00:00","end":"2019-04-09T23:52:30+00:00"},{"stap_id":"73","longitude":37.75,"latitude":-12.75,"duration_days":0.62,"start":"2019-04-10T02:57:30+00:00","end":"2019-04-10T17:52:30+00:00"},{"stap_id":"74","longitude":37.75,"latitude":-12.75,"duration_days":0.08,"start":"2019-04-10T18:52:30+00:00","end":"2019-04-10T20:47:30+00:00"},{"stap_id":"75","longitude":37.75,"latitude":-12.75,"duration_days":0.13,"start":"2019-04-10T21:47:30+00:00","end":"2019-04-11T00:52:30+00:00"},{"stap_id":"76","longitude":37.75,"latitude":-12.25,"duration_days":0.74,"start":"2019-04-11T02:42:30+00:00","end":"2019-04-11T20:32:30+00:00"},{"stap_id":"77","longitude":38.75,"latitude":-11.25,"duration_days":5.57,"start":"2019-04-12T02:47:30+00:00","end":"2019-04-17T16:32:30+00:00"},{"stap_id":"78","longitude":39.25,"latitude":-8.25,"duration_days":0.57,"start":"2019-04-18T02:52:30+00:00","end":"2019-04-18T16:27:30+00:00"},{"stap_id":"79","longitude":39.25,"latitude":-3.25,"duration_days":0.78,"start":"2019-04-19T01:32:30+00:00","end":"2019-04-19T20:22:30+00:00"},{"stap_id":"80","longitude":39.75,"latitude":-2.75,"duration_days":2.76,"start":"2019-04-19T22:42:30+00:00","end":"2019-04-22T17:02:30+00:00"},{"stap_id":"81","longitude":41.25,"latitude":0.75,"duration_days":6.57,"start":"2019-04-23T02:52:30+00:00","end":"2019-04-29T16:32:30+00:00"},{"stap_id":"82","longitude":41.25,"latitude":2.25,"duration_days":0.15,"start":"2019-04-29T20:37:30+00:00","end":"2019-04-30T00:07:30+00:00"},{"stap_id":"83","longitude":41.25,"latitude":3.25,"duration_days":0.55,"start":"2019-04-30T02:27:30+00:00","end":"2019-04-30T15:32:30+00:00"},{"stap_id":"84","longitude":44.25,"latitude":5.25,"duration_days":0.57,"start":"2019-05-01T02:22:30+00:00","end":"2019-05-01T16:02:30+00:00"},{"stap_id":"85","longitude":46.25,"latitude":7.25,"duration_days":0.56,"start":"2019-05-02T02:07:30+00:00","end":"2019-05-02T15:27:30+00:00"},{"stap_id":"86","longitude":47.75,"latitude":10.75,"duration_days":0.56,"start":"2019-05-03T02:02:30+00:00","end":"2019-05-03T15:27:30+00:00"},{"stap_id":"87","longitude":50.25,"latitude":11.25,"duration_days":0.55,"start":"2019-05-04T02:02:30+00:00","end":"2019-05-04T15:17:30+00:00"},{"stap_id":"88","longitude":49.25,"latitude":14.75,"duration_days":0.56,"start":"2019-05-05T01:57:30+00:00","end":"2019-05-05T15:22:30+00:00"},{"stap_id":"89","longitude":52.25,"latitude":15.75,"duration_days":0.58,"start":"2019-05-06T01:47:30+00:00","end":"2019-05-06T15:37:30+00:00"},{"stap_id":"90","longitude":54.75,"latitude":18.75,"duration_days":0.56,"start":"2019-05-07T01:37:30+00:00","end":"2019-05-07T15:07:30+00:00"},{"stap_id":"91","longitude":58.25,"latitude":22.25,"duration_days":0.6,"start":"2019-05-08T01:17:30+00:00","end":"2019-05-08T15:47:30+00:00"},{"stap_id":"92","longitude":58.25,"latitude":25.75,"duration_days":0.62,"start":"2019-05-09T01:02:30+00:00","end":"2019-05-09T15:57:30+00:00"},{"stap_id":"93","longitude":59.75,"latitude":28.25,"duration_days":0.68,"start":"2019-05-09T23:32:30+00:00","end":"2019-05-10T15:57:30+00:00"},{"stap_id":"94","longitude":63.25,"latitude":29.75,"duration_days":3.83,"start":"2019-05-11T00:47:30+00:00","end":"2019-05-14T20:47:30+00:00"},{"stap_id":"95","longitude":63.25,"latitude":31.25,"duration_days":0.63,"start":"2019-05-15T00:37:30+00:00","end":"2019-05-15T15:42:30+00:00"},{"stap_id":"96","longitude":63.25,"latitude":33.25,"duration_days":6.65,"start":"2019-05-16T00:12:30+00:00","end":"2019-05-22T15:42:30+00:00"},{"stap_id":"97","longitude":64.75,"latitude":35.25,"duration_days":0.61,"start":"2019-05-23T00:12:30+00:00","end":"2019-05-23T14:57:30+00:00"},{"stap_id":"98","longitude":66.75,"latitude":38.25,"duration_days":0.66,"start":"2019-05-23T23:52:30+00:00","end":"2019-05-24T15:37:30+00:00"},{"stap_id":"99","longitude":69.75,"latitude":40.75,"duration_days":0.65,"start":"2019-05-24T23:32:30+00:00","end":"2019-05-25T15:07:30+00:00"},{"stap_id":"100","longitude":71.75,"latitude":42.25,"duration_days":0.69,"start":"2019-05-25T23:12:30+00:00","end":"2019-05-26T15:52:30+00:00"},{"stap_id":"101","longitude":72.25,"latitude":43.75,"duration_days":0.71,"start":"2019-05-26T23:02:30+00:00","end":"2019-05-27T16:02:30+00:00"},{"stap_id":"102","longitude":69.75,"latitude":43.25,"duration_days":0.67,"start":"2019-05-27T22:47:30+00:00","end":"2019-05-28T14:52:30+00:00"},{"stap_id":"103","longitude":69.75,"latitude":43.25,"duration_days":1.03,"start":"2019-05-28T15:37:30+00:00","end":"2019-05-29T16:17:30+00:00"},{"stap_id":"104","longitude":71.75,"latitude":42.75,"duration_days":0.71,"start":"2019-05-29T22:27:30+00:00","end":"2019-05-30T15:27:30+00:00"},{"stap_id":"105","longitude":73.75,"latitude":44.75,"duration_days":0.38,"start":"2019-05-30T22:07:30+00:00","end":"2019-05-31T07:12:30+00:00"}]},{"tag_id":"24FD","scientific_name":"Caprimulgus europaeus","common_name":"Eurasian Nightjar","species_code":"eurnig1","in_ebirdst":true,"sex":"M","age_class":">2yr","wing_length":205.0,"staps":[{"stap_id":"1","longitude":110.83,"latitude":48.57,"duration_days":59.58,"start":"2019-06-14T23:57:30+00:00","end":"2019-08-13T13:52:30+00:00"},{"stap_id":"2","longitude":109.75,"latitude":48.25,"duration_days":0.77,"start":"2019-08-13T17:37:30+00:00","end":"2019-08-14T12:12:30+00:00"},{"stap_id":"3","longitude":106.25,"latitude":47.75,"duration_days":0.81,"start":"2019-08-14T19:37:30+00:00","end":"2019-08-15T15:07:30+00:00"},{"stap_id":"4","longitude":103.75,"latitude":46.75,"duration_days":10.66,"start":"2019-08-15T20:22:30+00:00","end":"2019-08-26T12:17:30+00:00"},{"stap_id":"5","longitude":99.25,"latitude":45.25,"duration_days":0.62,"start":"2019-08-26T21:52:30+00:00","end":"2019-08-27T12:47:30+00:00"},{"stap_id":"6","longitude":94.75,"latitude":46.25,"duration_days":0.67,"start":"2019-08-27T21:57:30+00:00","end":"2019-08-28T14:07:30+00:00"},{"stap_id":"7","longitude":93.25,"latitude":46.75,"duration_days":0.88,"start":"2019-08-28T17:32:30+00:00","end":"2019-08-29T14:42:30+00:00"},{"stap_id":"8","longitude":89.75,"latitude":46.25,"duration_days":0.71,"start":"2019-08-29T20:52:30+00:00","end":"2019-08-30T13:52:30+00:00"},{"stap_id":"9","longitude":85.25,"latitude":45.75,"duration_days":0.66,"start":"2019-08-30T22:22:30+00:00","end":"2019-08-31T14:17:30+00:00"},{"stap_id":"10","longitude":84.25,"latitude":45.75,"duration_days":0.1,"start":"2019-08-31T17:02:30+00:00","end":"2019-08-31T19:32:30+00:00"},{"stap_id":"11","longitude":83.75,"latitude":45.25,"duration_days":0.64,"start":"2019-08-31T22:27:30+00:00","end":"2019-09-01T13:52:30+00:00"},{"stap_id":"12","longitude":78.75,"latitude":44.75,"duration_days":0.62,"start":"2019-09-01T22:52:30+00:00","end":"2019-09-02T13:42:30+00:00"},{"stap_id":"13","longitude":74.25,"latitude":44.25,"duration_days":0.7,"start":"2019-09-02T22:02:30+00:00","end":"2019-09-03T14:57:30+00:00"},{"stap_id":"14","longitude":70.75,"latitude":42.25,"duration_days":16.65,"start":"2019-09-03T23:02:30+00:00","end":"2019-09-20T14:37:30+00:00"},{"stap_id":"15","longitude":69.75,"latitude":41.25,"duration_days":0.81,"start":"2019-09-20T18:47:30+00:00","end":"2019-09-21T14:07:30+00:00"},{"stap_id":"16","longitude":66.75,"latitude":41.25,"duration_days":0.8,"start":"2019-09-21T19:47:30+00:00","end":"2019-09-22T15:02:30+00:00"},{"stap_id":"17","longitude":66.75,"latitude":40.25,"duration_days":0.15,"start":"2019-09-22T17:12:30+00:00","end":"2019-09-22T20:42:30+00:00"},{"stap_id":"18","longitude":64.75,"latitude":39.75,"duration_days":0.58,"start":"2019-09-23T00:52:30+00:00","end":"2019-09-23T14:42:30+00:00"},{"stap_id":"19","longitude":61.25,"latitude":34.75,"duration_days":0.56,"start":"2019-09-24T00:57:30+00:00","end":"2019-09-24T14:17:30+00:00"},{"stap_id":"20","longitude":60.25,"latitude":33.75,"duration_days":0.16,"start":"2019-09-24T17:02:30+00:00","end":"2019-09-24T20:57:30+00:00"},{"stap_id":"21","longitude":60.75,"latitude":31.75,"duration_days":0.69,"start":"2019-09-25T00:52:30+00:00","end":"2019-09-25T17:32:30+00:00"},{"stap_id":"22","longitude":59.25,"latitude":29.25,"duration_days":0.6,"start":"2019-09-26T00:27:30+00:00","end":"2019-09-26T14:47:30+00:00"},{"stap_id":"23","longitude":56.25,"latitude":26.25,"duration_days":0.64,"start":"2019-09-27T01:37:30+00:00","end":"2019-09-27T16:57:30+00:00"},{"stap_id":"24","longitude":55.75,"latitude":25.25,"duration_days":0.74,"start":"2019-09-27T20:47:30+00:00","end":"2019-09-28T14:32:30+00:00"},{"stap_id":"25","longitude":56.25,"latitude":23.25,"duration_days":0.03,"start":"2019-09-28T22:12:30+00:00","end":"2019-09-28T22:57:30+00:00"},{"stap_id":"26","longitude":56.25,"latitude":23.25,"duration_days":0.64,"start":"2019-09-28T23:32:30+00:00","end":"2019-09-29T14:52:30+00:00"},{"stap_id":"27","longitude":53.25,"latitude":19.75,"duration_days":0.53,"start":"2019-09-30T01:52:30+00:00","end":"2019-09-30T14:42:30+00:00"},{"stap_id":"28","longitude":49.25,"latitude":16.75,"duration_days":0.59,"start":"2019-10-01T02:02:30+00:00","end":"2019-10-01T16:07:30+00:00"},{"stap_id":"29","longitude":48.25,"latitude":15.25,"duration_days":0.63,"start":"2019-10-01T23:47:30+00:00","end":"2019-10-02T14:52:30+00:00"},{"stap_id":"30","longitude":47.25,"latitude":13.75,"duration_days":13.79,"start":"2019-10-02T19:52:30+00:00","end":"2019-10-16T14:47:30+00:00"},{"stap_id":"31","longitude":46.75,"latitude":13.75,"duration_days":0.94,"start":"2019-10-16T16:12:30+00:00","end":"2019-10-17T14:52:30+00:00"},{"stap_id":"32","longitude":44.25,"latitude":6.75,"duration_days":1.61,"start":"2019-10-18T01:52:30+00:00","end":"2019-10-19T16:27:30+00:00"},{"stap_id":"33","longitude":44.25,"latitude":5.75,"duration_days":0.84,"start":"2019-10-19T20:52:30+00:00","end":"2019-10-20T16:57:30+00:00"},{"stap_id":"34","longitude":43.75,"latitude":3.75,"duration_days":0.87,"start":"2019-10-20T21:42:30+00:00","end":"2019-10-21T18:32:30+00:00"},{"stap_id":"35","longitude":43.75,"latitude":3.75,"duration_days":9.85,"start":"2019-10-21T19:42:30+00:00","end":"2019-10-31T16:07:30+00:00"},{"stap_id":"36","longitude":43.75,"latitude":3.25,"duration_days":5.18,"start":"2019-10-31T18:17:30+00:00","end":"2019-11-05T22:37:30+00:00"},{"stap_id":"37","longitude":42.75,"latitude":2.75,"duration_days":0.52,"start":"2019-11-06T02:27:30+00:00","end":"2019-11-06T14:57:30+00:00"},{"stap_id":"38","longitude":39.75,"latitude":-0.25,"duration_days":0.55,"start":"2019-11-07T02:12:30+00:00","end":"2019-11-07T15:22:30+00:00"},{"stap_id":"39","longitude":38.75,"latitude":-2.75,"duration_days":0.59,"start":"2019-11-08T01:12:30+00:00","end":"2019-11-08T15:27:30+00:00"},{"stap_id":"40","longitude":38.25,"latitude":-5.25,"duration_days":5.78,"start":"2019-11-09T00:17:30+00:00","end":"2019-11-14T18:57:30+00:00"},{"stap_id":"41","longitude":36.75,"latitude":-7.75,"duration_days":0.58,"start":"2019-11-15T02:12:30+00:00","end":"2019-11-15T16:07:30+00:00"},{"stap_id":"42","longitude":34.75,"latitude":-13.75,"duration_days":0.58,"start":"2019-11-16T02:27:30+00:00","end":"2019-11-16T16:27:30+00:00"},{"stap_id":"43","longitude":34.75,"latitude":-16.75,"duration_days":0.69,"start":"2019-11-17T00:17:30+00:00","end":"2019-11-17T16:57:30+00:00"},{"stap_id":"44","longitude":33.25,"latitude":-22.75,"duration_days":0.77,"start":"2019-11-18T02:07:30+00:00","end":"2019-11-18T20:37:30+00:00"},{"stap_id":"45","longitude":32.75,"latitude":-23.75,"duration_days":0.7,"start":"2019-11-19T00:17:30+00:00","end":"2019-11-19T17:02:30+00:00"},{"stap_id":"46","longitude":32.25,"latitude":-24.75,"duration_days":1.91,"start":"2019-11-19T19:22:30+00:00","end":"2019-11-21T17:17:30+00:00"},{"stap_id":"47","longitude":30.25,"latitude":-27.75,"duration_days":0.65,"start":"2019-11-22T02:17:30+00:00","end":"2019-11-22T17:57:30+00:00"},{"stap_id":"48","longitude":28.25,"latitude":-30.75,"duration_days":0.61,"start":"2019-11-23T02:32:30+00:00","end":"2019-11-23T17:12:30+00:00"},{"stap_id":"49","longitude":27.25,"latitude":-31.25,"duration_days":0.89,"start":"2019-11-23T21:22:30+00:00","end":"2019-11-24T18:42:30+00:00"},{"stap_id":"50","longitude":24.25,"latitude":-32.75,"duration_days":0.71,"start":"2019-11-25T02:17:30+00:00","end":"2019-11-25T19:22:30+00:00"},{"stap_id":"51","longitude":23.75,"latitude":-32.75,"duration_days":0.16,"start":"2019-11-25T20:22:30+00:00","end":"2019-11-26T00:12:30+00:00"},{"stap_id":"52","longitude":23.75,"latitude":-32.75,"duration_days":118.75,"start":"2019-11-26T01:17:30+00:00","end":"2020-03-23T19:12:30+00:00"},{"stap_id":"53","longitude":27.75,"latitude":-31.75,"duration_days":0.69,"start":"2020-03-24T03:27:30+00:00","end":"2020-03-24T20:02:30+00:00"},{"stap_id":"54","longitude":29.75,"latitude":-30.75,"duration_days":0.56,"start":"2020-03-25T03:02:30+00:00","end":"2020-03-25T16:22:30+00:00"},{"stap_id":"55","longitude":31.25,"latitude":-29.25,"duration_days":0.82,"start":"2020-03-25T20:22:30+00:00","end":"2020-03-26T16:07:30+00:00"},{"stap_id":"56","longitude":31.75,"latitude":-27.25,"duration_days":0.07,"start":"2020-03-26T21:27:30+00:00","end":"2020-03-26T23:07:30+00:00"},{"stap_id":"57","longitude":31.75,"latitude":-26.75,"duration_days":0.63,"start":"2020-03-27T00:52:30+00:00","end":"2020-03-27T15:57:30+00:00"},{"stap_id":"58","longitude":31.75,"latitude":-26.25,"duration_days":0.16,"start":"2020-03-27T17:27:30+00:00","end":"2020-03-27T21:17:30+00:00"},{"stap_id":"59","longitude":33.25,"latitude":-24.75,"duration_days":0.55,"start":"2020-03-28T03:17:30+00:00","end":"2020-03-28T16:22:30+00:00"},{"stap_id":"60","longitude":35.25,"latitude":-21.75,"duration_days":0.55,"start":"2020-03-29T03:12:30+00:00","end":"2020-03-29T16:27:30+00:00"},{"stap_id":"61","longitude":37.25,"latitude":-17.25,"duration_days":0.55,"start":"2020-03-30T02:57:30+00:00","end":"2020-03-30T16:12:30+00:00"},{"stap_id":"62","longitude":39.75,"latitude":-13.25,"duration_days":0.54,"start":"2020-03-31T02:47:30+00:00","end":"2020-03-31T15:42:30+00:00"},{"stap_id":"63","longitude":39.75,"latitude":-9.25,"duration_days":0.56,"start":"2020-04-01T03:02:30+00:00","end":"2020-04-01T16:22:30+00:00"},{"stap_id":"64","longitude":39.25,"latitude":-5.75,"duration_days":0.84,"start":"2020-04-02T02:12:30+00:00","end":"2020-04-02T22:17:30+00:00"},{"stap_id":"65","longitude":39.75,"latitude":-4.25,"duration_days":0.52,"start":"2020-04-03T02:52:30+00:00","end":"2020-04-03T15:27:30+00:00"},{"stap_id":"66","longitude":41.25,"latitude":-1.75,"duration_days":0.04,"start":"2020-04-03T21:47:30+00:00","end":"2020-04-03T22:47:30+00:00"},{"stap_id":"67","longitude":42.25,"latitude":-0.75,"duration_days":6.56,"start":"2020-04-04T02:52:30+00:00","end":"2020-04-10T16:12:30+00:00"},{"stap_id":"68","longitude":42.75,"latitude":-0.25,"duration_days":2.97,"start":"2020-04-10T18:02:30+00:00","end":"2020-04-13T17:17:30+00:00"},{"stap_id":"69","longitude":42.75,"latitude":0.25,"duration_days":1.27,"start":"2020-04-13T18:42:30+00:00","end":"2020-04-15T01:07:30+00:00"},{"stap_id":"70","longitude":42.75,"latitude":0.75,"duration_days":3.64,"start":"2020-04-15T02:32:30+00:00","end":"2020-04-18T17:52:30+00:00"},{"stap_id":"71","longitude":43.25,"latitude":1.25,"duration_days":1.77,"start":"2020-04-18T20:32:30+00:00","end":"2020-04-20T15:02:30+00:00"},{"stap_id":"72","longitude":44.75,"latitude":2.25,"duration_days":3.85,"start":"2020-04-20T19:17:30+00:00","end":"2020-04-24T15:42:30+00:00"},{"stap_id":"73","longitude":47.25,"latitude":3.75,"duration_days":0.66,"start":"2020-04-24T23:17:30+00:00","end":"2020-04-25T15:07:30+00:00"},{"stap_id":"74","longitude":49.25,"latitude":7.75,"duration_days":0.56,"start":"2020-04-26T01:47:30+00:00","end":"2020-04-26T15:12:30+00:00"},{"stap_id":"75","longitude":50.25,"latitude":8.75,"duration_days":0.82,"start":"2020-04-26T19:27:30+00:00","end":"2020-04-27T15:07:30+00:00"},{"stap_id":"76","longitude":53.75,"latitude":12.75,"duration_days":0.56,"start":"2020-04-28T01:47:30+00:00","end":"2020-04-28T15:12:30+00:00"},{"stap_id":"77","longitude":53.25,"latitude":16.75,"duration_days":0.57,"start":"2020-04-29T01:32:30+00:00","end":"2020-04-29T15:07:30+00:00"},{"stap_id":"78","longitude":55.75,"latitude":21.75,"duration_days":0.57,"start":"2020-04-30T01:22:30+00:00","end":"2020-04-30T15:07:30+00:00"},{"stap_id":"79","longitude":55.75,"latitude":25.25,"duration_days":0.76,"start":"2020-04-30T20:57:30+00:00","end":"2020-05-01T15:17:30+00:00"},{"stap_id":"80","longitude":60.75,"latitude":28.75,"duration_days":0.62,"start":"2020-05-02T00:37:30+00:00","end":"2020-05-02T15:37:30+00:00"},{"stap_id":"81","longitude":61.25,"latitude":31.25,"duration_days":0.68,"start":"2020-05-02T23:32:30+00:00","end":"2020-05-03T15:57:30+00:00"},{"stap_id":"82","longitude":62.75,"latitude":34.75,"duration_days":0.62,"start":"2020-05-04T00:17:30+00:00","end":"2020-05-04T15:07:30+00:00"},{"stap_id":"83","longitude":66.25,"latitude":36.25,"duration_days":0.61,"start":"2020-05-04T23:52:30+00:00","end":"2020-05-05T14:37:30+00:00"},{"stap_id":"84","longitude":66.25,"latitude":37.25,"duration_days":0.08,"start":"2020-05-05T18:07:30+00:00","end":"2020-05-05T20:02:30+00:00"},{"stap_id":"85","longitude":66.25,"latitude":37.75,"duration_days":0.66,"start":"2020-05-05T22:47:30+00:00","end":"2020-05-06T14:42:30+00:00"},{"stap_id":"86","longitude":67.75,"latitude":39.75,"duration_days":0.68,"start":"2020-05-06T22:57:30+00:00","end":"2020-05-07T15:17:30+00:00"},{"stap_id":"87","longitude":68.25,"latitude":40.75,"duration_days":0.95,"start":"2020-05-07T18:12:30+00:00","end":"2020-05-08T16:57:30+00:00"},{"stap_id":"88","longitude":69.75,"latitude":43.75,"duration_days":0.68,"start":"2020-05-08T23:27:30+00:00","end":"2020-05-09T15:47:30+00:00"},{"stap_id":"89","longitude":70.75,"latitude":44.25,"duration_days":3.9,"start":"2020-05-09T17:32:30+00:00","end":"2020-05-13T15:02:30+00:00"},{"stap_id":"90","longitude":76.25,"latitude":44.25,"duration_days":0.73,"start":"2020-05-13T21:02:30+00:00","end":"2020-05-14T14:27:30+00:00"},{"stap_id":"91","longitude":81.75,"latitude":44.25,"duration_days":0.69,"start":"2020-05-14T22:02:30+00:00","end":"2020-05-15T14:42:30+00:00"},{"stap_id":"92","longitude":86.75,"latitude":45.75,"duration_days":0.69,"start":"2020-05-15T22:07:30+00:00","end":"2020-05-16T14:42:30+00:00"},{"stap_id":"93","longitude":90.75,"latitude":46.75,"duration_days":0.67,"start":"2020-05-16T21:32:30+00:00","end":"2020-05-17T13:37:30+00:00"},{"stap_id":"94","longitude":93.75,"latitude":47.25,"duration_days":0.67,"start":"2020-05-17T21:17:30+00:00","end":"2020-05-18T13:17:30+00:00"},{"stap_id":"95","longitude":98.75,"latitude":46.25,"duration_days":0.7,"start":"2020-05-18T20:52:30+00:00","end":"2020-05-19T13:47:30+00:00"},{"stap_id":"96","longitude":101.25,"latitude":46.75,"duration_days":0.86,"start":"2020-05-19T20:37:30+00:00","end":"2020-05-20T17:17:30+00:00"},{"stap_id":"97","longitude":102.75,"latitude":46.75,"duration_days":0.78,"start":"2020-05-20T20:42:30+00:00","end":"2020-05-21T15:22:30+00:00"},{"stap_id":"98","longitude":103.25,"latitude":45.75,"duration_days":4.85,"start":"2020-05-21T18:42:30+00:00","end":"2020-05-26T15:12:30+00:00"},{"stap_id":"99","longitude":106.25,"latitude":46.25,"duration_days":0.76,"start":"2020-05-26T20:17:30+00:00","end":"2020-05-27T14:32:30+00:00"},{"stap_id":"100","longitude":109.75,"latitude":47.75,"duration_days":0.72,"start":"2020-05-27T19:12:30+00:00","end":"2020-05-28T12:22:30+00:00"},{"stap_id":"101","longitude":109.75,"latitude":47.75,"duration_days":1.13,"start":"2020-05-28T13:12:30+00:00","end":"2020-05-29T16:22:30+00:00"},{"stap_id":"102","longitude":110.25,"latitude":47.75,"duration_days":0.82,"start":"2020-05-29T17:22:30+00:00","end":"2020-05-30T13:02:30+00:00"},{"stap_id":"103","longitude":110.25,"latitude":47.75,"duration_days":1.01,"start":"2020-05-30T13:42:30+00:00","end":"2020-05-31T13:52:30+00:00"},{"stap_id":"104","longitude":110.75,"latitude":48.75,"duration_days":0.81,"start":"2020-05-31T17:32:30+00:00","end":"2020-06-01T12:52:30+00:00"},{"stap_id":"105","longitude":110.83,"latitude":48.57,"duration_days":76.96,"start":"2020-06-01T13:47:30+00:00","end":"2020-08-17T12:52:30+00:00"},{"stap_id":"106","longitude":106.25,"latitude":46.75,"duration_days":0.69,"start":"2020-08-17T20:32:30+00:00","end":"2020-08-18T13:07:30+00:00"},{"stap_id":"107","longitude":102.25,"latitude":47.75,"duration_days":0.78,"start":"2020-08-18T18:42:30+00:00","end":"2020-08-19T13:22:30+00:00"},{"stap_id":"108","longitude":100.75,"latitude":47.75,"duration_days":0.09,"start":"2020-08-19T16:07:30+00:00","end":"2020-08-19T18:22:30+00:00"},{"stap_id":"109","longitude":100.25,"latitude":47.75,"duration_days":0.77,"start":"2020-08-19T21:02:30+00:00","end":"2020-08-20T15:27:30+00:00"},{"stap_id":"110","longitude":96.75,"latitude":47.25,"duration_days":0.67,"start":"2020-08-20T21:42:30+00:00","end":"2020-08-21T13:52:30+00:00"},{"stap_id":"111","longitude":92.75,"latitude":47.25,"duration_days":0.66,"start":"2020-08-21T22:07:30+00:00","end":"2020-08-22T14:02:30+00:00"},{"stap_id":"112","longitude":89.25,"latitude":47.25,"duration_days":0.62,"start":"2020-08-22T22:12:30+00:00","end":"2020-08-23T13:02:30+00:00"},{"stap_id":"113","longitude":88.25,"latitude":46.75,"duration_days":0.91,"start":"2020-08-23T17:07:30+00:00","end":"2020-08-24T14:52:30+00:00"},{"stap_id":"114","longitude":84.75,"latitude":45.75,"duration_days":0.03,"start":"2020-08-24T19:42:30+00:00","end":"2020-08-24T20:27:30+00:00"},{"stap_id":"115","longitude":84.25,"latitude":45.75,"duration_days":1.76,"start":"2020-08-24T21:37:30+00:00","end":"2020-08-26T15:52:30+00:00"},{"stap_id":"116","longitude":82.75,"latitude":45.75,"duration_days":0.71,"start":"2020-08-26T20:57:30+00:00","end":"2020-08-27T14:02:30+00:00"},{"stap_id":"117","longitude":82.25,"latitude":45.75,"duration_days":0.06,"start":"2020-08-27T15:22:30+00:00","end":"2020-08-27T16:52:30+00:00"},{"stap_id":"118","longitude":81.75,"latitude":45.75,"duration_days":0.99,"start":"2020-08-27T18:17:30+00:00","end":"2020-08-28T18:02:30+00:00"},{"stap_id":"119","longitude":79.75,"latitude":44.75,"duration_days":0.88,"start":"2020-08-28T22:02:30+00:00","end":"2020-08-29T19:12:30+00:00"},{"stap_id":"120","longitude":79.75,"latitude":44.75,"duration_days":4.81,"start":"2020-08-29T19:57:30+00:00","end":"2020-09-03T15:22:30+00:00"},{"stap_id":"121","longitude":79.75,"latitude":44.75,"duration_days":0.07,"start":"2020-09-03T16:07:30+00:00","end":"2020-09-03T17:42:30+00:00"},{"stap_id":"122","longitude":78.25,"latitude":45.25,"duration_days":0.71,"start":"2020-09-03T20:42:30+00:00","end":"2020-09-04T13:42:30+00:00"},{"stap_id":"123","longitude":74.75,"latitude":43.75,"duration_days":0.77,"start":"2020-09-04T20:02:30+00:00","end":"2020-09-05T14:37:30+00:00"},{"stap_id":"124","longitude":71.75,"latitude":41.75,"duration_days":0.58,"start":"2020-09-05T23:57:30+00:00","end":"2020-09-06T13:47:30+00:00"},{"stap_id":"125","longitude":71.75,"latitude":41.75,"duration_days":0.11,"start":"2020-09-06T15:22:30+00:00","end":"2020-09-06T18:02:30+00:00"},{"stap_id":"126","longitude":71.25,"latitude":41.75,"duration_days":9.96,"start":"2020-09-06T20:07:30+00:00","end":"2020-09-16T19:07:30+00:00"},{"stap_id":"127","longitude":71.25,"latitude":41.75,"duration_days":0.93,"start":"2020-09-16T20:27:30+00:00","end":"2020-09-17T18:42:30+00:00"},{"stap_id":"128","longitude":70.25,"latitude":41.25,"duration_days":0.69,"start":"2020-09-17T21:32:30+00:00","end":"2020-09-18T14:07:30+00:00"},{"stap_id":"129","longitude":63.25,"latitude":38.75,"duration_days":0.6,"start":"2020-09-19T00:22:30+00:00","end":"2020-09-19T14:42:30+00:00"},{"stap_id":"130","longitude":59.25,"latitude":38.75,"duration_days":0.72,"start":"2020-09-19T21:57:30+00:00","end":"2020-09-20T15:12:30+00:00"},{"stap_id":"131","longitude":56.25,"latitude":37.25,"duration_days":0.66,"start":"2020-09-20T23:17:30+00:00","end":"2020-09-21T15:12:30+00:00"},{"stap_id":"132","longitude":53.75,"latitude":36.25,"duration_days":0.66,"start":"2020-09-21T23:52:30+00:00","end":"2020-09-22T15:37:30+00:00"},{"stap_id":"133","longitude":53.75,"latitude":36.25,"duration_days":1.1,"start":"2020-09-22T16:22:30+00:00","end":"2020-09-23T18:52:30+00:00"},{"stap_id":"134","longitude":53.75,"latitude":36.25,"duration_days":3.78,"start":"2020-09-23T19:52:30+00:00","end":"2020-09-27T14:37:30+00:00"},{"stap_id":"135","longitude":53.75,"latitude":35.75,"duration_days":1.08,"start":"2020-09-27T16:22:30+00:00","end":"2020-09-28T18:12:30+00:00"}]}],"known_locations":[{"latitude":48.593095,"longitude":110.689954,"location_name":"ONON RIVER","kind":"equipment"},{"latitude":48.383229,"longitude":110.176427,"location_name":"BINDERIYA KHAN MOUTAIN","kind":"equipment"}]}